{
  "$schema": "https://ui.shadcn.com/schema/registry-item.json",
  "name": "diff-view",
  "title": "Diff View",
  "description": "Unified diff with added/removed lines, gutter markers, and a stat summary.",
  "registryDependencies": [
    "badge"
  ],
  "files": [
    {
      "path": "registry/code/diff-view.tsx",
      "content": "import { cn } from \"@/lib/utils\"\nimport { Badge } from \"@/components/ui/badge\"\n\nexport interface DiffLine {\n  type: \"add\" | \"remove\" | \"context\"\n  text: string\n}\n\nconst DEFAULT_LINES: DiffLine[] = [\n  { type: \"context\", text: \"export function greet(name: string) {\" },\n  { type: \"remove\", text: '  return \"Hello \" + name' },\n  { type: \"add\", text: \"  return `Hello, ${name}!`\" },\n  { type: \"context\", text: \"}\" },\n  { type: \"context\", text: \"\" },\n  { type: \"remove\", text: \"const enabled = false\" },\n  { type: \"add\", text: \"const enabled = true\" },\n  { type: \"add\", text: \"const retries = 3\" },\n]\n\nexport function DiffView({\n  filename = \"src/greet.ts\",\n  lines = DEFAULT_LINES,\n  className,\n}: {\n  filename?: string\n  lines?: DiffLine[]\n  className?: string\n}) {\n  const additions = lines.filter((l) => l.type === \"add\").length\n  const deletions = lines.filter((l) => l.type === \"remove\").length\n\n  let oldNo = 0\n  let newNo = 0\n\n  return (\n    <div\n      dir=\"ltr\"\n      className={cn(\n        \"w-full max-w-lg overflow-hidden rounded-xl border bg-card font-mono text-[13px]\",\n        className\n      )}\n    >\n      <div className=\"flex items-center gap-2 border-b bg-muted/40 px-3 py-2\">\n        <span className=\"text-xs font-medium text-foreground\">{filename}</span>\n        <div className=\"ms-auto flex items-center gap-1.5\">\n          <Badge\n            variant=\"secondary\"\n            className=\"bg-emerald-500/10 text-emerald-600 dark:text-emerald-400\"\n          >\n            +{additions}\n          </Badge>\n          <Badge\n            variant=\"secondary\"\n            className=\"bg-rose-500/10 text-rose-600 dark:text-rose-400\"\n          >\n            −{deletions}\n          </Badge>\n        </div>\n      </div>\n\n      <div className=\"overflow-x-auto\">\n        {lines.map((line, i) => {\n          if (line.type !== \"add\") oldNo += 1\n          if (line.type !== \"remove\") newNo += 1\n          const sign =\n            line.type === \"add\" ? \"+\" : line.type === \"remove\" ? \"−\" : \" \"\n          return (\n            <div\n              key={i}\n              className={cn(\n                \"flex\",\n                line.type === \"add\" &&\n                  \"bg-emerald-500/10 text-emerald-700 dark:text-emerald-300\",\n                line.type === \"remove\" &&\n                  \"bg-rose-500/10 text-rose-700 dark:text-rose-300\"\n              )}\n            >\n              <span className=\"w-9 shrink-0 select-none px-1 text-end text-muted-foreground/50 tabular-nums\">\n                {line.type === \"add\" ? \"\" : oldNo}\n              </span>\n              <span className=\"w-9 shrink-0 select-none px-1 text-end text-muted-foreground/50 tabular-nums\">\n                {line.type === \"remove\" ? \"\" : newNo}\n              </span>\n              <span\n                className={cn(\n                  \"w-5 shrink-0 select-none text-center\",\n                  line.type === \"add\" && \"text-emerald-500\",\n                  line.type === \"remove\" && \"text-rose-500\",\n                  line.type === \"context\" && \"text-transparent\"\n                )}\n              >\n                {sign}\n              </span>\n              <code className=\"flex-1 whitespace-pre pe-3\">\n                {line.text || \" \"}\n              </code>\n            </div>\n          )\n        })}\n      </div>\n    </div>\n  )\n}\n",
      "type": "registry:component"
    }
  ],
  "type": "registry:component"
}